setup.py
sux/__init__.py
sux/operator_hackiness.py
sux/pickle_fixer.py
sux/py2helper.py
sux.egg-info/PKG-INFO
sux.egg-info/SOURCES.txt
sux.egg-info/dependency_links.txt
sux.egg-info/requires.txt
sux.egg-info/top_level.txt
tests/__init__.py
tests/conftest.py
tests/test_boto.py
tests/test_env.py
tests/test_garbage_collection.py
tests/test_native.py
tests/test_native_args.py
tests/test_sys.py
tests/test_urlparse.py