Metadata-Version: 1.1
Name: sux
Version: 0.1.5
Summary: Transparently use python2 packages from python3
Home-page: https://github.com/nicois/sux/blob/master/README.md
Author: Nicholas Farrell
Author-email: nicholas.farrell@gmail.com
License: BSD
Keywords: python3
Platform: UNKNOWN
Classifier: Development Status :: 4 - Beta
Classifier: Intended Audience :: Developers
Classifier: Programming Language :: Python :: 3
Classifier: Topic :: Software Development
Classifier: License :: OSI Approved :: BSD License
